{
    "0": [
        [
            357,
            395
        ],
        [
            365,
            365
        ],
        [
            0,
            0
        ],
        [
            430,
            367
        ],
        [
            0,
            0
        ],
        [
            495,
            512
        ],
        [
            591,
            481
        ],
        [
            243,
            716
        ],
        [
            404,
            733
        ],
        [
            233,
            525
        ],
        [
            316,
            632
        ],
        [
            596,
            964
        ],
        [
            646,
            926
        ],
        [
            0,
            0
        ],
        [
            0,
            0
        ],
        [
            0,
            0
        ],
        [
            0,
            0
        ],
        [
            189.0,
            202.0,
            781.0,
            1069.0
        ]
    ],
    "1": [
        [
            356,
            394
        ],
        [
            365,
            364
        ],
        [
            0,
            0
        ],
        [
            429,
            365
        ],
        [
            0,
            0
        ],
        [
            490,
            517
        ],
        [
            594,
            486
        ],
        [
            234,
            722
        ],
        [
            404,
            739
        ],
        [
            240,
            504
        ],
        [
            313,
            632
        ],
        [
            571,
            973
        ],
        [
            632,
            937
        ],
        [
            0,
            0
        ],
        [
            0,
            0
        ],
        [
            0,
            0
        ],
        [
            0,
            0
        ],
        [
            187.0,
            201.0,
            781.0,
            1070.0
        ]
    ],
    "2": [
        [
            355,
            394
        ],
        [
            364,
            364
        ],
        [
            0,
            0
        ],
        [
            429,
            366
        ],
        [
            0,
            0
        ],
        [
            488,
            517
        ],
        [
            596,
            488
        ],
        [
            236,
            723
        ],
        [
            408,
            747
        ],
        [
            236,
            518
        ],
        [
            316,
            675
        ],
        [
            570,
            970
        ],
        [
            634,
            934
        ],
        [
            0,
            0
        ],
        [
            0,
            0
        ],
        [
            0,
            0
        ],
        [
            0,
            0
        ],
        [
            187.0,
            203.0,
            781.0,
            1070.0
        ]
    ],
    "3": [
        [
            354,
            393
        ],
        [
            363,
            363
        ],
        [
            0,
            0
        ],
        [
            428,
            365
        ],
        [
            0,
            0
        ],
        [
            488,
            517
        ],
        [
            589,
            487
        ],
        [
            232,
            726
        ],
        [
            399,
            741
        ],
        [
            236,
            515
        ],
        [
            308,
            640
        ],
        [
            572,
            967
        ],
        [
            631,
            932
        ],
        [
            0,
            0
        ],
        [
            0,
            0
        ],
        [
            0,
            0
        ],
        [
            0,
            0
        ],
        [
            187.0,
            202.0,
            780.0,
            1070.0
        ]
    ],
    "4": [
        [
            354,
            396
        ],
        [
            362,
            366
        ],
        [
            0,
            0
        ],
        [
            426,
            367
        ],
        [
            0,
            0
        ],
        [
            495,
            511
        ],
        [
            580,
            483
        ],
        [
            243,
            712
        ],
        [
            401,
            744
        ],
        [
            229,
            542
        ],
        [
            327,
            719
        ],
        [
            597,
            956
        ],
        [
            639,
            920
        ],
        [
            0,
            0
        ],
        [
            0,
            0
        ],
        [
            0,
            0
        ],
        [
            0,
            0
        ],
        [
            189.0,
            202.0,
            780.0,
            1069.0
        ]
    ],
    "5": [
        [
            353,
            397
        ],
        [
            361,
            367
        ],
        [
            0,
            0
        ],
        [
            425,
            369
        ],
        [
            0,
            0
        ],
        [
            495,
            511
        ],
        [
            578,
            484
        ],
        [
            246,
            708
        ],
        [
            401,
            744
        ],
        [
            231,
            542
        ],
        [
            329,
            736
        ],
        [
            598,
            952
        ],
        [
            637,
            917
        ],
        [
            0,
            0
        ],
        [
            0,
            0
        ],
        [
            0,
            0
        ],
        [
            0,
            0
        ],
        [
            189.0,
            201.0,
            780.0,
            1069.0
        ]
    ],
    "6": [
        [
            353,
            398
        ],
        [
            361,
            368
        ],
        [
            0,
            0
        ],
        [
            425,
            370
        ],
        [
            0,
            0
        ],
        [
            495,
            511
        ],
        [
            582,
            484
        ],
        [
            247,
            706
        ],
        [
            410,
            743
        ],
        [
            231,
            542
        ],
        [
            332,
            743
        ],
        [
            597,
            950
        ],
        [
            639,
            915
        ],
        [
            0,
            0
        ],
        [
            0,
            0
        ],
        [
            0,
            0
        ],
        [
            0,
            0
        ],
        [
            189.0,
            202.0,
            781.0,
            1069.0
        ]
    ],
    "7": [
        [
            353,
            398
        ],
        [
            361,
            368
        ],
        [
            0,
            0
        ],
        [
            425,
            370
        ],
        [
            0,
            0
        ],
        [
            496,
            511
        ],
        [
            578,
            483
        ],
        [
            247,
            708
        ],
        [
            404,
            745
        ],
        [
            233,
            544
        ],
        [
            327,
            728
        ],
        [
            598,
            950
        ],
        [
            637,
            915
        ],
        [
            0,
            0
        ],
        [
            0,
            0
        ],
        [
            0,
            0
        ],
        [
            0,
            0
        ],
        [
            189.0,
            202.0,
            781.0,
            1069.0
        ]
    ],
    "8": [
        [
            353,
            398
        ],
        [
            361,
            368
        ],
        [
            0,
            0
        ],
        [
            425,
            370
        ],
        [
            0,
            0
        ],
        [
            496,
            511
        ],
        [
            575,
            483
        ],
        [
            247,
            711
        ],
        [
            399,
            745
        ],
        [
            234,
            548
        ],
        [
            324,
            720
        ],
        [
            598,
            951
        ],
        [
            636,
            916
        ],
        [
            0,
            0
        ],
        [
            0,
            0
        ],
        [
            0,
            0
        ],
        [
            0,
            0
        ],
        [
            189.0,
            201.0,
            781.0,
            1069.0
        ]
    ],
    "9": [
        [
            353,
            398
        ],
        [
            361,
            368
        ],
        [
            0,
            0
        ],
        [
            425,
            370
        ],
        [
            0,
            0
        ],
        [
            496,
            511
        ],
        [
            575,
            483
        ],
        [
            246,
            712
        ],
        [
            397,
            745
        ],
        [
            235,
            548
        ],
        [
            323,
            713
        ],
        [
            598,
            950
        ],
        [
            636,
            915
        ],
        [
            0,
            0
        ],
        [
            0,
            0
        ],
        [
            0,
            0
        ],
        [
            0,
            0
        ],
        [
            189.0,
            201.0,
            781.0,
            1069.0
        ]
    ],
    "10": [
        [
            354,
            398
        ],
        [
            362,
            369
        ],
        [
            0,
            0
        ],
        [
            426,
            370
        ],
        [
            0,
            0
        ],
        [
            494,
            511
        ],
        [
            579,
            483
        ],
        [
            245,
            715
        ],
        [
            399,
            744
        ],
        [
            237,
            549
        ],
        [
            323,
            705
        ],
        [
            598,
            952
        ],
        [
            640,
            917
        ],
        [
            0,
            0
        ],
        [
            0,
            0
        ],
        [
            0,
            0
        ],
        [
            0,
            0
        ],
        [
            190.0,
            201.0,
            782.0,
            1069.0
        ]
    ],
    "11": [
        [
            354,
            399
        ],
        [
            362,
            369
        ],
        [
            0,
            0
        ],
        [
            426,
            370
        ],
        [
            0,
            0
        ],
        [
            496,
            511
        ],
        [
            580,
            482
        ],
        [
            247,
            713
        ],
        [
            401,
            744
        ],
        [
            236,
            548
        ],
        [
            326,
            718
        ],
        [
            599,
            952
        ],
        [
            640,
            917
        ],
        [
            0,
            0
        ],
        [
            0,
            0
        ],
        [
            0,
            0
        ],
        [
            0,
            0
        ],
        [
            190.0,
            202.0,
            781.0,
            1069.0
        ]
    ],
    "12": [
        [
            355,
            398
        ],
        [
            363,
            368
        ],
        [
            0,
            0
        ],
        [
            427,
            369
        ],
        [
            0,
            0
        ],
        [
            489,
            517
        ],
        [
            587,
            488
        ],
        [
            239,
            719
        ],
        [
            409,
            751
        ],
        [
            244,
            530
        ],
        [
            331,
            733
        ],
        [
            574,
            959
        ],
        [
            628,
            926
        ],
        [
            0,
            0
        ],
        [
            0,
            0
        ],
        [
            0,
            0
        ],
        [
            0,
            0
        ],
        [
            189.0,
            203.0,
            781.0,
            1070.0
        ]
    ],
    "13": [
        [
            355,
            399
        ],
        [
            363,
            369
        ],
        [
            0,
            0
        ],
        [
            427,
            369
        ],
        [
            0,
            0
        ],
        [
            488,
            518
        ],
        [
            587,
            489
        ],
        [
            236,
            726
        ],
        [
            403,
            749
        ],
        [
            243,
            527
        ],
        [
            319,
            684
        ],
        [
            569,
            970
        ],
        [
            626,
            935
        ],
        [
            0,
            0
        ],
        [
            0,
            0
        ],
        [
            0,
            0
        ],
        [
            0,
            0
        ],
        [
            189.0,
            203.0,
            781.0,
            1071.0
        ]
    ],
    "14": [
        [
            354,
            400
        ],
        [
            363,
            370
        ],
        [
            0,
            0
        ],
        [
            426,
            371
        ],
        [
            0,
            0
        ],
        [
            496,
            514
        ],
        [
            576,
            482
        ],
        [
            237,
            729
        ],
        [
            373,
            726
        ],
        [
            236,
            533
        ],
        [
            283,
            563
        ],
        [
            597,
            964
        ],
        [
            638,
            927
        ],
        [
            0,
            0
        ],
        [
            0,
            0
        ],
        [
            0,
            0
        ],
        [
            0,
            0
        ],
        [
            190.0,
            203.0,
            782.0,
            1070.0
        ]
    ],
    "15": [
        [
            355,
            400
        ],
        [
            364,
            370
        ],
        [
            0,
            0
        ],
        [
            427,
            371
        ],
        [
            0,
            0
        ],
        [
            496,
            514
        ],
        [
            577,
            481
        ],
        [
            235,
            728
        ],
        [
            373,
            723
        ],
        [
            237,
            534
        ],
        [
            288,
            563
        ],
        [
            597,
            966
        ],
        [
            639,
            928
        ],
        [
            0,
            0
        ],
        [
            0,
            0
        ],
        [
            0,
            0
        ],
        [
            0,
            0
        ],
        [
            190.0,
            203.0,
            782.0,
            1070.0
        ]
    ],
    "16": [
        [
            355,
            399
        ],
        [
            365,
            370
        ],
        [
            0,
            0
        ],
        [
            425,
            371
        ],
        [
            0,
            0
        ],
        [
            496,
            515
        ],
        [
            572,
            482
        ],
        [
            229,
            736
        ],
        [
            359,
            716
        ],
        [
            239,
            532
        ],
        [
            273,
            534
        ],
        [
            596,
            967
        ],
        [
            636,
            929
        ],
        [
            0,
            0
        ],
        [
            0,
            0
        ],
        [
            0,
            0
        ],
        [
            0,
            0
        ],
        [
            190.0,
            204.0,
            782.0,
            1070.0
        ]
    ],
    "17": [
        [
            356,
            399
        ],
        [
            365,
            369
        ],
        [
            0,
            0
        ],
        [
            427,
            371
        ],
        [
            0,
            0
        ],
        [
            498,
            515
        ],
        [
            574,
            482
        ],
        [
            232,
            732
        ],
        [
            363,
            720
        ],
        [
            238,
            531
        ],
        [
            277,
            542
        ],
        [
            596,
            970
        ],
        [
            635,
            932
        ],
        [
            0,
            0
        ],
        [
            0,
            0
        ],
        [
            0,
            0
        ],
        [
            0,
            0
        ],
        [
            190.0,
            203.0,
            782.0,
            1070.0
        ]
    ],
    "18": [
        [
            356,
            399
        ],
        [
            365,
            369
        ],
        [
            0,
            0
        ],
        [
            427,
            371
        ],
        [
            0,
            0
        ],
        [
            496,
            515
        ],
        [
            579,
            481
        ],
        [
            233,
            731
        ],
        [
            369,
            718
        ],
        [
            238,
            532
        ],
        [
            284,
            548
        ],
        [
            594,
            969
        ],
        [
            639,
            930
        ],
        [
            0,
            0
        ],
        [
            0,
            0
        ],
        [
            0,
            0
        ],
        [
            0,
            0
        ],
        [
            190.0,
            203.0,
            782.0,
            1071.0
        ]
    ],
    "19": [
        [
            355,
            399
        ],
        [
            365,
            369
        ],
        [
            0,
            0
        ],
        [
            427,
            371
        ],
        [
            0,
            0
        ],
        [
            495,
            517
        ],
        [
            576,
            482
        ],
        [
            230,
            735
        ],
        [
            364,
            717
        ],
        [
            238,
            531
        ],
        [
            276,
            538
        ],
        [
            594,
            972
        ],
        [
            638,
            933
        ],
        [
            0,
            0
        ],
        [
            0,
            0
        ],
        [
            0,
            0
        ],
        [
            0,
            0
        ],
        [
            190.0,
            203.0,
            782.0,
            1071.0
        ]
    ],
    "20": [
        [
            356,
            399
        ],
        [
            365,
            369
        ],
        [
            0,
            0
        ],
        [
            428,
            371
        ],
        [
            0,
            0
        ],
        [
            495,
            516
        ],
        [
            580,
            482
        ],
        [
            233,
            730
        ],
        [
            371,
            719
        ],
        [
            237,
            533
        ],
        [
            286,
            551
        ],
        [
            590,
            978
        ],
        [
            636,
            939
        ],
        [
            0,
            0
        ],
        [
            0,
            0
        ],
        [
            0,
            0
        ],
        [
            0,
            0
        ],
        [
            190.0,
            203.0,
            782.0,
            1070.0
        ]
    ],
    "21": [
        [
            355,
            399
        ],
        [
            365,
            369
        ],
        [
            0,
            0
        ],
        [
            427,
            371
        ],
        [
            0,
            0
        ],
        [
            496,
            517
        ],
        [
            577,
            482
        ],
        [
            232,
            733
        ],
        [
            367,
            717
        ],
        [
            237,
            533
        ],
        [
            283,
            544
        ],
        [
            591,
            977
        ],
        [
            635,
            938
        ],
        [
            0,
            0
        ],
        [
            0,
            0
        ],
        [
            0,
            0
        ],
        [
            0,
            0
        ],
        [
            190.0,
            202.0,
            782.0,
            1070.0
        ]
    ],
    "22": [
        [
            354,
            398
        ],
        [
            364,
            368
        ],
        [
            0,
            0
        ],
        [
            427,
            371
        ],
        [
            0,
            0
        ],
        [
            496,
            517
        ],
        [
            576,
            483
        ],
        [
            231,
            733
        ],
        [
            368,
            719
        ],
        [
            237,
            532
        ],
        [
            290,
            544
        ],
        [
            592,
            979
        ],
        [
            633,
            940
        ],
        [
            0,
            0
        ],
        [
            0,
            0
        ],
        [
            0,
            0
        ],
        [
            0,
            0
        ],
        [
            190.0,
            203.0,
            782.0,
            1070.0
        ]
    ],
    "23": [
        [
            355,
            397
        ],
        [
            364,
            367
        ],
        [
            0,
            0
        ],
        [
            428,
            369
        ],
        [
            0,
            0
        ],
        [
            487,
            521
        ],
        [
            592,
            489
        ],
        [
            232,
            730
        ],
        [
            399,
            737
        ],
        [
            240,
            524
        ],
        [
            305,
            611
        ],
        [
            567,
            983
        ],
        [
            630,
            946
        ],
        [
            0,
            0
        ],
        [
            0,
            0
        ],
        [
            0,
            0
        ],
        [
            0,
            0
        ],
        [
            188.0,
            203.0,
            781.0,
            1070.0
        ]
    ],
    "24": [
        [
            355,
            399
        ],
        [
            364,
            369
        ],
        [
            0,
            0
        ],
        [
            427,
            371
        ],
        [
            0,
            0
        ],
        [
            490,
            519
        ],
        [
            588,
            482
        ],
        [
            227,
            733
        ],
        [
            385,
            708
        ],
        [
            237,
            533
        ],
        [
            310,
            542
        ],
        [
            592,
            976
        ],
        [
            646,
            937
        ],
        [
            0,
            0
        ],
        [
            0,
            0
        ],
        [
            0,
            0
        ],
        [
            0,
            0
        ],
        [
            189.0,
            204.0,
            780.0,
            1070.0
        ]
    ],
    "25": [
        [
            355,
            399
        ],
        [
            364,
            368
        ],
        [
            0,
            0
        ],
        [
            427,
            371
        ],
        [
            0,
            0
        ],
        [
            490,
            519
        ],
        [
            588,
            482
        ],
        [
            226,
            733
        ],
        [
            384,
            710
        ],
        [
            230,
            533
        ],
        [
            303,
            543
        ],
        [
            592,
            976
        ],
        [
            646,
            937
        ],
        [
            0,
            0
        ],
        [
            0,
            0
        ],
        [
            0,
            0
        ],
        [
            0,
            0
        ],
        [
            188.0,
            203.0,
            780.0,
            1070.0
        ]
    ],
    "26": [
        [
            355,
            398
        ],
        [
            364,
            367
        ],
        [
            0,
            0
        ],
        [
            428,
            370
        ],
        [
            0,
            0
        ],
        [
            488,
            518
        ],
        [
            596,
            483
        ],
        [
            229,
            730
        ],
        [
            394,
            716
        ],
        [
            226,
            530
        ],
        [
            297,
            553
        ],
        [
            591,
            975
        ],
        [
            653,
            936
        ],
        [
            0,
            0
        ],
        [
            0,
            0
        ],
        [
            0,
            0
        ],
        [
            0,
            0
        ],
        [
            186.0,
            203.0,
            780.0,
            1070.0
        ]
    ],
    "27": [
        [
            354,
            398
        ],
        [
            363,
            367
        ],
        [
            0,
            0
        ],
        [
            425,
            370
        ],
        [
            0,
            0
        ],
        [
            488,
            519
        ],
        [
            591,
            484
        ],
        [
            222,
            738
        ],
        [
            379,
            712
        ],
        [
            225,
            517
        ],
        [
            273,
            515
        ],
        [
            593,
            972
        ],
        [
            653,
            933
        ],
        [
            0,
            0
        ],
        [
            0,
            0
        ],
        [
            0,
            0
        ],
        [
            0,
            0
        ],
        [
            184.0,
            202.0,
            781.0,
            1070.0
        ]
    ],
    "28": [
        [
            354,
            398
        ],
        [
            363,
            368
        ],
        [
            0,
            0
        ],
        [
            425,
            371
        ],
        [
            0,
            0
        ],
        [
            489,
            518
        ],
        [
            590,
            483
        ],
        [
            221,
            735
        ],
        [
            377,
            712
        ],
        [
            223,
            516
        ],
        [
            272,
            515
        ],
        [
            595,
            970
        ],
        [
            653,
            931
        ],
        [
            0,
            0
        ],
        [
            0,
            0
        ],
        [
            0,
            0
        ],
        [
            0,
            0
        ],
        [
            184.0,
            202.0,
            781.0,
            1070.0
        ]
    ],
    "29": [
        [
            354,
            398
        ],
        [
            363,
            367
        ],
        [
            0,
            0
        ],
        [
            426,
            370
        ],
        [
            0,
            0
        ],
        [
            492,
            518
        ],
        [
            583,
            483
        ],
        [
            224,
            735
        ],
        [
            370,
            711
        ],
        [
            222,
            517
        ],
        [
            267,
            516
        ],
        [
            597,
            973
        ],
        [
            647,
            934
        ],
        [
            0,
            0
        ],
        [
            0,
            0
        ],
        [
            0,
            0
        ],
        [
            0,
            0
        ],
        [
            183.0,
            202.0,
            780.0,
            1070.0
        ]
    ],
    "30": [
        [
            353,
            397
        ],
        [
            363,
            367
        ],
        [
            0,
            0
        ],
        [
            425,
            370
        ],
        [
            0,
            0
        ],
        [
            493,
            517
        ],
        [
            579,
            483
        ],
        [
            224,
            734
        ],
        [
            369,
            711
        ],
        [
            219,
            523
        ],
        [
            268,
            522
        ],
        [
            599,
            969
        ],
        [
            645,
            930
        ],
        [
            0,
            0
        ],
        [
            0,
            0
        ],
        [
            0,
            0
        ],
        [
            0,
            0
        ],
        [
            184.0,
            204.0,
            780.0,
            1069.0
        ]
    ],
    "31": [
        [
            354,
            396
        ],
        [
            364,
            366
        ],
        [
            0,
            0
        ],
        [
            429,
            368
        ],
        [
            0,
            0
        ],
        [
            486,
            520
        ],
        [
            589,
            488
        ],
        [
            233,
            730
        ],
        [
            402,
            731
        ],
        [
            229,
            531
        ],
        [
            308,
            595
        ],
        [
            577,
            966
        ],
        [
            636,
            931
        ],
        [
            0,
            0
        ],
        [
            0,
            0
        ],
        [
            0,
            0
        ],
        [
            0,
            0
        ],
        [
            184.0,
            204.0,
            779.0,
            1069.0
        ]
    ],
    "32": [
        [
            353,
            395
        ],
        [
            363,
            365
        ],
        [
            0,
            0
        ],
        [
            428,
            368
        ],
        [
            0,
            0
        ],
        [
            487,
            521
        ],
        [
            585,
            488
        ],
        [
            231,
            730
        ],
        [
            389,
            721
        ],
        [
            231,
            519
        ],
        [
            289,
            551
        ],
        [
            578,
            967
        ],
        [
            635,
            932
        ],
        [
            0,
            0
        ],
        [
            0,
            0
        ],
        [
            0,
            0
        ],
        [
            0,
            0
        ],
        [
            184.0,
            204.0,
            779.0,
            1069.0
        ]
    ],
    "33": [
        [
            354,
            396
        ],
        [
            364,
            366
        ],
        [
            0,
            0
        ],
        [
            427,
            371
        ],
        [
            0,
            0
        ],
        [
            492,
            517
        ],
        [
            578,
            484
        ],
        [
            230,
            732
        ],
        [
            378,
            717
        ],
        [
            234,
            534
        ],
        [
            295,
            540
        ],
        [
            599,
            963
        ],
        [
            644,
            926
        ],
        [
            0,
            0
        ],
        [
            0,
            0
        ],
        [
            0,
            0
        ],
        [
            0,
            0
        ],
        [
            188.0,
            203.0,
            780.0,
            1069.0
        ]
    ],
    "34": [
        [
            354,
            395
        ],
        [
            364,
            366
        ],
        [
            0,
            0
        ],
        [
            426,
            371
        ],
        [
            0,
            0
        ],
        [
            490,
            519
        ],
        [
            580,
            483
        ],
        [
            230,
            734
        ],
        [
            379,
            713
        ],
        [
            237,
            534
        ],
        [
            296,
            538
        ],
        [
            599,
            964
        ],
        [
            647,
            926
        ],
        [
            0,
            0
        ],
        [
            0,
            0
        ],
        [
            0,
            0
        ],
        [
            0,
            0
        ],
        [
            189.0,
            203.0,
            780.0,
            1069.0
        ]
    ],
    "35": [
        [
            354,
            396
        ],
        [
            364,
            366
        ],
        [
            0,
            0
        ],
        [
            428,
            371
        ],
        [
            0,
            0
        ],
        [
            492,
            518
        ],
        [
            580,
            483
        ],
        [
            234,
            730
        ],
        [
            383,
            713
        ],
        [
            234,
            538
        ],
        [
            306,
            551
        ],
        [
            598,
            965
        ],
        [
            644,
            927
        ],
        [
            0,
            0
        ],
        [
            0,
            0
        ],
        [
            0,
            0
        ],
        [
            0,
            0
        ],
        [
            189.0,
            203.0,
            780.0,
            1069.0
        ]
    ],
    "36": [
        [
            355,
            396
        ],
        [
            364,
            366
        ],
        [
            0,
            0
        ],
        [
            429,
            371
        ],
        [
            0,
            0
        ],
        [
            494,
            517
        ],
        [
            581,
            484
        ],
        [
            241,
            724
        ],
        [
            390,
            724
        ],
        [
            230,
            544
        ],
        [
            309,
            601
        ],
        [
            598,
            963
        ],
        [
            643,
            926
        ],
        [
            0,
            0
        ],
        [
            0,
            0
        ],
        [
            0,
            0
        ],
        [
            0,
            0
        ],
        [
            188.0,
            204.0,
            780.0,
            1069.0
        ]
    ],
    "37": [
        [
            355,
            396
        ],
        [
            365,
            366
        ],
        [
            0,
            0
        ],
        [
            428,
            370
        ],
        [
            0,
            0
        ],
        [
            492,
            518
        ],
        [
            579,
            483
        ],
        [
            231,
            732
        ],
        [
            374,
            714
        ],
        [
            231,
            531
        ],
        [
            280,
            537
        ],
        [
            599,
            965
        ],
        [
            645,
            927
        ],
        [
            0,
            0
        ],
        [
            0,
            0
        ],
        [
            0,
            0
        ],
        [
            0,
            0
        ],
        [
            188.0,
            203.0,
            781.0,
            1069.0
        ]
    ],
    "38": [
        [
            355,
            396
        ],
        [
            365,
            366
        ],
        [
            0,
            0
        ],
        [
            428,
            371
        ],
        [
            0,
            0
        ],
        [
            492,
            517
        ],
        [
            582,
            482
        ],
        [
            235,
            728
        ],
        [
            385,
            714
        ],
        [
            230,
            538
        ],
        [
            299,
            557
        ],
        [
            599,
            965
        ],
        [
            646,
            927
        ],
        [
            0,
            0
        ],
        [
            0,
            0
        ],
        [
            0,
            0
        ],
        [
            0,
            0
        ],
        [
            189.0,
            202.0,
            780.0,
            1069.0
        ]
    ],
    "39": [
        [
            355,
            396
        ],
        [
            365,
            366
        ],
        [
            0,
            0
        ],
        [
            428,
            371
        ],
        [
            0,
            0
        ],
        [
            489,
            519
        ],
        [
            588,
            482
        ],
        [
            234,
            728
        ],
        [
            394,
            713
        ],
        [
            228,
            539
        ],
        [
            309,
            563
        ],
        [
            597,
            968
        ],
        [
            650,
            929
        ],
        [
            0,
            0
        ],
        [
            0,
            0
        ],
        [
            0,
            0
        ],
        [
            0,
            0
        ],
        [
            188.0,
            202.0,
            781.0,
            1069.0
        ]
    ],
    "40": [
        [
            354,
            395
        ],
        [
            365,
            365
        ],
        [
            0,
            0
        ],
        [
            431,
            367
        ],
        [
            0,
            0
        ],
        [
            486,
            519
        ],
        [
            582,
            483
        ],
        [
            239,
            720
        ],
        [
            399,
            715
        ],
        [
            226,
            530
        ],
        [
            304,
            604
        ],
        [
            583,
            972
        ],
        [
            640,
            935
        ],
        [
            0,
            0
        ],
        [
            0,
            0
        ],
        [
            0,
            0
        ],
        [
            0,
            0
        ],
        [
            185.0,
            207.0,
            780.0,
            1068.0
        ]
    ],
    "41": [
        [
            355,
            395
        ],
        [
            365,
            365
        ],
        [
            0,
            0
        ],
        [
            430,
            367
        ],
        [
            0,
            0
        ],
        [
            487,
            519
        ],
        [
            580,
            482
        ],
        [
            238,
            720
        ],
        [
            398,
            710
        ],
        [
            225,
            530
        ],
        [
            307,
            576
        ],
        [
            583,
            970
        ],
        [
            638,
            933
        ],
        [
            0,
            0
        ],
        [
            0,
            0
        ],
        [
            0,
            0
        ],
        [
            0,
            0
        ],
        [
            183.0,
            208.0,
            780.0,
            1068.0
        ]
    ],
    "42": [
        [
            355,
            394
        ],
        [
            365,
            364
        ],
        [
            0,
            0
        ],
        [
            430,
            366
        ],
        [
            0,
            0
        ],
        [
            487,
            518
        ],
        [
            579,
            483
        ],
        [
            238,
            721
        ],
        [
            393,
            712
        ],
        [
            223,
            529
        ],
        [
            295,
            569
        ],
        [
            584,
            971
        ],
        [
            638,
            934
        ],
        [
            0,
            0
        ],
        [
            0,
            0
        ],
        [
            0,
            0
        ],
        [
            0,
            0
        ],
        [
            183.0,
            208.0,
            780.0,
            1068.0
        ]
    ],
    "43": [
        [
            355,
            395
        ],
        [
            365,
            366
        ],
        [
            0,
            0
        ],
        [
            428,
            371
        ],
        [
            0,
            0
        ],
        [
            488,
            518
        ],
        [
            588,
            483
        ],
        [
            230,
            730
        ],
        [
            391,
            713
        ],
        [
            222,
            538
        ],
        [
            299,
            549
        ],
        [
            597,
            964
        ],
        [
            652,
            926
        ],
        [
            0,
            0
        ],
        [
            0,
            0
        ],
        [
            0,
            0
        ],
        [
            0,
            0
        ],
        [
            185.0,
            202.0,
            781.0,
            1070.0
        ]
    ],
    "44": [
        [
            355,
            395
        ],
        [
            365,
            365
        ],
        [
            0,
            0
        ],
        [
            427,
            370
        ],
        [
            0,
            0
        ],
        [
            490,
            517
        ],
        [
            582,
            482
        ],
        [
            230,
            731
        ],
        [
            380,
            713
        ],
        [
            227,
            532
        ],
        [
            291,
            537
        ],
        [
            600,
            962
        ],
        [
            650,
            924
        ],
        [
            0,
            0
        ],
        [
            0,
            0
        ],
        [
            0,
            0
        ],
        [
            0,
            0
        ],
        [
            180.0,
            203.0,
            780.0,
            1070.0
        ]
    ],
    "45": [
        [
            355,
            394
        ],
        [
            365,
            364
        ],
        [
            0,
            0
        ],
        [
            429,
            368
        ],
        [
            0,
            0
        ],
        [
            486,
            521
        ],
        [
            586,
            487
        ],
        [
            231,
            733
        ],
        [
            387,
            716
        ],
        [
            230,
            519
        ],
        [
            285,
            531
        ],
        [
            577,
            969
        ],
        [
            637,
            932
        ],
        [
            0,
            0
        ],
        [
            0,
            0
        ],
        [
            0,
            0
        ],
        [
            0,
            0
        ],
        [
            175.0,
            203.0,
            779.0,
            1070.0
        ]
    ],
    "46": [
        [
            355,
            394
        ],
        [
            365,
            364
        ],
        [
            0,
            0
        ],
        [
            429,
            368
        ],
        [
            0,
            0
        ],
        [
            486,
            522
        ],
        [
            587,
            487
        ],
        [
            231,
            733
        ],
        [
            393,
            715
        ],
        [
            229,
            524
        ],
        [
            298,
            540
        ],
        [
            572,
            976
        ],
        [
            632,
            938
        ],
        [
            0,
            0
        ],
        [
            0,
            0
        ],
        [
            0,
            0
        ],
        [
            0,
            0
        ],
        [
            176.0,
            203.0,
            778.0,
            1071.0
        ]
    ],
    "47": [
        [
            355,
            394
        ],
        [
            365,
            365
        ],
        [
            0,
            0
        ],
        [
            429,
            369
        ],
        [
            0,
            0
        ],
        [
            486,
            522
        ],
        [
            589,
            486
        ],
        [
            231,
            730
        ],
        [
            400,
            713
        ],
        [
            229,
            527
        ],
        [
            311,
            551
        ],
        [
            574,
            972
        ],
        [
            634,
            934
        ],
        [
            0,
            0
        ],
        [
            0,
            0
        ],
        [
            0,
            0
        ],
        [
            0,
            0
        ],
        [
            175.0,
            202.0,
            778.0,
            1071.0
        ]
    ],
    "48": [
        [
            355,
            395
        ],
        [
            365,
            365
        ],
        [
            0,
            0
        ],
        [
            432,
            365
        ],
        [
            0,
            0
        ],
        [
            490,
            518
        ],
        [
            584,
            485
        ],
        [
            241,
            712
        ],
        [
            406,
            730
        ],
        [
            223,
            529
        ],
        [
            318,
            681
        ],
        [
            584,
            975
        ],
        [
            638,
            938
        ],
        [
            0,
            0
        ],
        [
            0,
            0
        ],
        [
            0,
            0
        ],
        [
            0,
            0
        ],
        [
            174.0,
            205.0,
            778.0,
            1069.0
        ]
    ],
    "49": [
        [
            356,
            395
        ],
        [
            366,
            364
        ],
        [
            0,
            0
        ],
        [
            433,
            365
        ],
        [
            0,
            0
        ],
        [
            490,
            518
        ],
        [
            581,
            485
        ],
        [
            240,
            716
        ],
        [
            398,
            720
        ],
        [
            222,
            528
        ],
        [
            306,
            619
        ],
        [
            584,
            975
        ],
        [
            636,
            939
        ],
        [
            0,
            0
        ],
        [
            0,
            0
        ],
        [
            0,
            0
        ],
        [
            0,
            0
        ],
        [
            173.0,
            206.0,
            778.0,
            1069.0
        ]
    ],
    "50": [
        [
            356,
            394
        ],
        [
            366,
            364
        ],
        [
            0,
            0
        ],
        [
            431,
            367
        ],
        [
            0,
            0
        ],
        [
            489,
            521
        ],
        [
            587,
            487
        ],
        [
            233,
            730
        ],
        [
            392,
            720
        ],
        [
            228,
            525
        ],
        [
            0,
            0
        ],
        [
            574,
            975
        ],
        [
            632,
            938
        ],
        [
            0,
            0
        ],
        [
            0,
            0
        ],
        [
            0,
            0
        ],
        [
            0,
            0
        ],
        [
            176.0,
            202.0,
            778.0,
            1071.0
        ]
    ],
    "51": [
        [
            356,
            394
        ],
        [
            366,
            364
        ],
        [
            0,
            0
        ],
        [
            431,
            367
        ],
        [
            0,
            0
        ],
        [
            488,
            521
        ],
        [
            587,
            486
        ],
        [
            233,
            729
        ],
        [
            399,
            723
        ],
        [
            231,
            527
        ],
        [
            309,
            595
        ],
        [
            572,
            975
        ],
        [
            629,
            938
        ],
        [
            0,
            0
        ],
        [
            0,
            0
        ],
        [
            0,
            0
        ],
        [
            0,
            0
        ],
        [
            183.0,
            201.0,
            778.0,
            1071.0
        ]
    ],
    "52": [
        [
            356,
            394
        ],
        [
            366,
            364
        ],
        [
            0,
            0
        ],
        [
            431,
            367
        ],
        [
            0,
            0
        ],
        [
            488,
            522
        ],
        [
            584,
            484
        ],
        [
            231,
            730
        ],
        [
            392,
            710
        ],
        [
            231,
            527
        ],
        [
            311,
            565
        ],
        [
            571,
            976
        ],
        [
            627,
            938
        ],
        [
            0,
            0
        ],
        [
            0,
            0
        ],
        [
            0,
            0
        ],
        [
            0,
            0
        ],
        [
            185.0,
            201.0,
            778.0,
            1071.0
        ]
    ],
    "53": [
        [
            356,
            393
        ],
        [
            367,
            364
        ],
        [
            0,
            0
        ],
        [
            431,
            367
        ],
        [
            0,
            0
        ],
        [
            487,
            521
        ],
        [
            585,
            485
        ],
        [
            231,
            731
        ],
        [
            395,
            711
        ],
        [
            229,
            528
        ],
        [
            310,
            555
        ],
        [
            572,
            975
        ],
        [
            629,
            937
        ],
        [
            0,
            0
        ],
        [
            0,
            0
        ],
        [
            0,
            0
        ],
        [
            0,
            0
        ],
        [
            184.0,
            201.0,
            779.0,
            1071.0
        ]
    ],
    "54": [
        [
            356,
            394
        ],
        [
            367,
            364
        ],
        [
            0,
            0
        ],
        [
            432,
            365
        ],
        [
            0,
            0
        ],
        [
            489,
            519
        ],
        [
            580,
            482
        ],
        [
            235,
            723
        ],
        [
            392,
            706
        ],
        [
            223,
            530
        ],
        [
            302,
            559
        ],
        [
            581,
            978
        ],
        [
            635,
            940
        ],
        [
            0,
            0
        ],
        [
            0,
            0
        ],
        [
            0,
            0
        ],
        [
            0,
            0
        ],
        [
            182.0,
            207.0,
            779.0,
            1069.0
        ]
    ],
    "55": [
        [
            356,
            394
        ],
        [
            367,
            364
        ],
        [
            0,
            0
        ],
        [
            433,
            365
        ],
        [
            0,
            0
        ],
        [
            489,
            519
        ],
        [
            581,
            482
        ],
        [
            235,
            719
        ],
        [
            398,
            711
        ],
        [
            221,
            530
        ],
        [
            314,
            599
        ],
        [
            580,
            979
        ],
        [
            633,
            941
        ],
        [
            0,
            0
        ],
        [
            0,
            0
        ],
        [
            0,
            0
        ],
        [
            0,
            0
        ],
        [
            181.0,
            207.0,
            779.0,
            1069.0
        ]
    ],
    "56": [
        [
            356,
            394
        ],
        [
            367,
            364
        ],
        [
            0,
            0
        ],
        [
            434,
            365
        ],
        [
            0,
            0
        ],
        [
            490,
            518
        ],
        [
            579,
            483
        ],
        [
            239,
            717
        ],
        [
            398,
            718
        ],
        [
            222,
            534
        ],
        [
            314,
            635
        ],
        [
            583,
            975
        ],
        [
            634,
            938
        ],
        [
            0,
            0
        ],
        [
            0,
            0
        ],
        [
            0,
            0
        ],
        [
            0,
            0
        ],
        [
            179.0,
            206.0,
            778.0,
            1069.0
        ]
    ],
    "57": [
        [
            357,
            394
        ],
        [
            367,
            364
        ],
        [
            0,
            0
        ],
        [
            433,
            366
        ],
        [
            0,
            0
        ],
        [
            490,
            518
        ],
        [
            581,
            484
        ],
        [
            234,
            727
        ],
        [
            398,
            720
        ],
        [
            226,
            530
        ],
        [
            318,
            596
        ],
        [
            572,
            969
        ],
        [
            624,
            933
        ],
        [
            0,
            0
        ],
        [
            0,
            0
        ],
        [
            0,
            0
        ],
        [
            0,
            0
        ],
        [
            174.0,
            201.0,
            778.0,
            1071.0
        ]
    ],
    "58": [
        [
            357,
            393
        ],
        [
            367,
            364
        ],
        [
            0,
            0
        ],
        [
            432,
            367
        ],
        [
            0,
            0
        ],
        [
            490,
            520
        ],
        [
            581,
            484
        ],
        [
            233,
            729
        ],
        [
            392,
            713
        ],
        [
            227,
            524
        ],
        [
            311,
            565
        ],
        [
            573,
            972
        ],
        [
            624,
            935
        ],
        [
            0,
            0
        ],
        [
            0,
            0
        ],
        [
            0,
            0
        ],
        [
            0,
            0
        ],
        [
            171.0,
            201.0,
            779.0,
            1070.0
        ]
    ],
    "59": [
        [
            357,
            393
        ],
        [
            367,
            363
        ],
        [
            0,
            0
        ],
        [
            432,
            367
        ],
        [
            0,
            0
        ],
        [
            489,
            520
        ],
        [
            580,
            484
        ],
        [
            232,
            729
        ],
        [
            392,
            710
        ],
        [
            229,
            525
        ],
        [
            312,
            552
        ],
        [
            572,
            970
        ],
        [
            624,
            933
        ],
        [
            0,
            0
        ],
        [
            0,
            0
        ],
        [
            0,
            0
        ],
        [
            0,
            0
        ],
        [
            173.0,
            202.0,
            779.0,
            1070.0
        ]
    ],
    "60": [
        [
            357,
            393
        ],
        [
            367,
            363
        ],
        [
            0,
            0
        ],
        [
            432,
            367
        ],
        [
            0,
            0
        ],
        [
            489,
            520
        ],
        [
            580,
            484
        ],
        [
            231,
            730
        ],
        [
            390,
            709
        ],
        [
            232,
            526
        ],
        [
            313,
            545
        ],
        [
            571,
            971
        ],
        [
            623,
            934
        ],
        [
            0,
            0
        ],
        [
            0,
            0
        ],
        [
            0,
            0
        ],
        [
            0,
            0
        ],
        [
            175.0,
            201.0,
            779.0,
            1070.0
        ]
    ],
    "61": [
        [
            357,
            394
        ],
        [
            367,
            364
        ],
        [
            0,
            0
        ],
        [
            433,
            367
        ],
        [
            0,
            0
        ],
        [
            490,
            520
        ],
        [
            580,
            485
        ],
        [
            232,
            729
        ],
        [
            390,
            714
        ],
        [
            232,
            526
        ],
        [
            314,
            567
        ],
        [
            572,
            971
        ],
        [
            622,
            934
        ],
        [
            0,
            0
        ],
        [
            0,
            0
        ],
        [
            0,
            0
        ],
        [
            0,
            0
        ],
        [
            177.0,
            201.0,
            778.0,
            1070.0
        ]
    ],
    "62": [
        [
            357,
            394
        ],
        [
            367,
            364
        ],
        [
            0,
            0
        ],
        [
            433,
            366
        ],
        [
            0,
            0
        ],
        [
            490,
            519
        ],
        [
            577,
            485
        ],
        [
            232,
            730
        ],
        [
            390,
            715
        ],
        [
            234,
            533
        ],
        [
            316,
            567
        ],
        [
            571,
            970
        ],
        [
            620,
            934
        ],
        [
            0,
            0
        ],
        [
            0,
            0
        ],
        [
            0,
            0
        ],
        [
            0,
            0
        ],
        [
            182.0,
            201.0,
            779.0,
            1070.0
        ]
    ],
    "63": [
        [
            357,
            393
        ],
        [
            367,
            363
        ],
        [
            0,
            0
        ],
        [
            432,
            367
        ],
        [
            0,
            0
        ],
        [
            488,
            520
        ],
        [
            578,
            485
        ],
        [
            230,
            733
        ],
        [
            390,
            712
        ],
        [
            234,
            533
        ],
        [
            317,
            550
        ],
        [
            570,
            970
        ],
        [
            621,
            933
        ],
        [
            0,
            0
        ],
        [
            0,
            0
        ],
        [
            0,
            0
        ],
        [
            0,
            0
        ],
        [
            186.0,
            201.0,
            778.0,
            1070.0
        ]
    ],
    "64": [
        [
            356,
            394
        ],
        [
            368,
            363
        ],
        [
            0,
            0
        ],
        [
            434,
            365
        ],
        [
            0,
            0
        ],
        [
            489,
            519
        ],
        [
            573,
            483
        ],
        [
            234,
            724
        ],
        [
            391,
            708
        ],
        [
            227,
            534
        ],
        [
            313,
            563
        ],
        [
            580,
            975
        ],
        [
            628,
            937
        ],
        [
            0,
            0
        ],
        [
            0,
            0
        ],
        [
            0,
            0
        ],
        [
            0,
            0
        ],
        [
            184.0,
            206.0,
            779.0,
            1068.0
        ]
    ],
    "65": [
        [
            357,
            393
        ],
        [
            368,
            363
        ],
        [
            0,
            0
        ],
        [
            434,
            365
        ],
        [
            0,
            0
        ],
        [
            488,
            519
        ],
        [
            575,
            483
        ],
        [
            233,
            725
        ],
        [
            392,
            706
        ],
        [
            226,
            536
        ],
        [
            314,
            555
        ],
        [
            579,
            974
        ],
        [
            629,
            936
        ],
        [
            0,
            0
        ],
        [
            0,
            0
        ],
        [
            0,
            0
        ],
        [
            0,
            0
        ],
        [
            183.0,
            205.0,
            779.0,
            1068.0
        ]
    ],
    "66": [
        [
            357,
            394
        ],
        [
            368,
            363
        ],
        [
            0,
            0
        ],
        [
            435,
            364
        ],
        [
            0,
            0
        ],
        [
            489,
            518
        ],
        [
            576,
            484
        ],
        [
            236,
            721
        ],
        [
            393,
            715
        ],
        [
            224,
            536
        ],
        [
            310,
            594
        ],
        [
            581,
            972
        ],
        [
            631,
            936
        ],
        [
            0,
            0
        ],
        [
            0,
            0
        ],
        [
            0,
            0
        ],
        [
            0,
            0
        ],
        [
            184.0,
            204.0,
            778.0,
            1068.0
        ]
    ],
    "67": [
        [
            358,
            393
        ],
        [
            368,
            363
        ],
        [
            0,
            0
        ],
        [
            434,
            366
        ],
        [
            0,
            0
        ],
        [
            490,
            518
        ],
        [
            581,
            485
        ],
        [
            233,
            729
        ],
        [
            398,
            722
        ],
        [
            229,
            536
        ],
        [
            322,
            596
        ],
        [
            573,
            966
        ],
        [
            624,
            930
        ],
        [
            0,
            0
        ],
        [
            0,
            0
        ],
        [
            0,
            0
        ],
        [
            0,
            0
        ],
        [
            184.0,
            201.0,
            778.0,
            1070.0
        ]
    ],
    "68": [
        [
            358,
            393
        ],
        [
            368,
            363
        ],
        [
            0,
            0
        ],
        [
            433,
            366
        ],
        [
            0,
            0
        ],
        [
            490,
            519
        ],
        [
            583,
            485
        ],
        [
            234,
            729
        ],
        [
            394,
            721
        ],
        [
            231,
            527
        ],
        [
            308,
            582
        ],
        [
            572,
            968
        ],
        [
            626,
            932
        ],
        [
            0,
            0
        ],
        [
            0,
            0
        ],
        [
            0,
            0
        ],
        [
            0,
            0
        ],
        [
            180.0,
            200.0,
            778.0,
            1070.0
        ]
    ],
    "69": [
        [
            358,
            393
        ],
        [
            368,
            363
        ],
        [
            0,
            0
        ],
        [
            433,
            366
        ],
        [
            0,
            0
        ],
        [
            490,
            518
        ],
        [
            586,
            486
        ],
        [
            238,
            725
        ],
        [
            404,
            732
        ],
        [
            232,
            534
        ],
        [
            320,
            645
        ],
        [
            572,
            968
        ],
        [
            625,
            932
        ],
        [
            0,
            0
        ],
        [
            0,
            0
        ],
        [
            0,
            0
        ],
        [
            0,
            0
        ],
        [
            182.0,
            200.0,
            778.0,
            1070.0
        ]
    ],
    "70": [
        [
            358,
            393
        ],
        [
            368,
            363
        ],
        [
            0,
            0
        ],
        [
            432,
            366
        ],
        [
            0,
            0
        ],
        [
            487,
            520
        ],
        [
            582,
            486
        ],
        [
            231,
            735
        ],
        [
            391,
            717
        ],
        [
            239,
            531
        ],
        [
            309,
            542
        ],
        [
            571,
            969
        ],
        [
            626,
            932
        ],
        [
            0,
            0
        ],
        [
            0,
            0
        ],
        [
            0,
            0
        ],
        [
            0,
            0
        ],
        [
            186.0,
            200.0,
            779.0,
            1070.0
        ]
    ],
    "71": [
        [
            358,
            393
        ],
        [
            368,
            363
        ],
        [
            0,
            0
        ],
        [
            432,
            366
        ],
        [
            0,
            0
        ],
        [
            487,
            519
        ],
        [
            581,
            485
        ],
        [
            230,
            738
        ],
        [
            391,
            717
        ],
        [
            238,
            536
        ],
        [
            313,
            546
        ],
        [
            570,
            968
        ],
        [
            625,
            932
        ],
        [
            0,
            0
        ],
        [
            0,
            0
        ],
        [
            0,
            0
        ],
        [
            0,
            0
        ],
        [
            188.0,
            200.0,
            779.0,
            1071.0
        ]
    ],
    "72": [
        [
            358,
            395
        ],
        [
            367,
            365
        ],
        [
            0,
            0
        ],
        [
            430,
            368
        ],
        [
            0,
            0
        ],
        [
            493,
            517
        ],
        [
            582,
            483
        ],
        [
            229,
            736
        ],
        [
            380,
            713
        ],
        [
            232,
            542
        ],
        [
            302,
            545
        ],
        [
            592,
            970
        ],
        [
            640,
            932
        ],
        [
            0,
            0
        ],
        [
            0,
            0
        ],
        [
            0,
            0
        ],
        [
            0,
            0
        ],
        [
            188.0,
            200.0,
            780.0,
            1070.0
        ]
    ],
    "73": [
        [
            359,
            394
        ],
        [
            368,
            364
        ],
        [
            0,
            0
        ],
        [
            431,
            368
        ],
        [
            0,
            0
        ],
        [
            491,
            517
        ],
        [
            585,
            482
        ],
        [
            228,
            735
        ],
        [
            384,
            710
        ],
        [
            232,
            540
        ],
        [
            308,
            542
        ],
        [
            592,
            970
        ],
        [
            643,
            932
        ],
        [
            0,
            0
        ],
        [
            0,
            0
        ],
        [
            0,
            0
        ],
        [
            0,
            0
        ],
        [
            187.0,
            200.0,
            781.0,
            1070.0
        ]
    ],
    "74": [
        [
            359,
            394
        ],
        [
            368,
            364
        ],
        [
            0,
            0
        ],
        [
            430,
            367
        ],
        [
            0,
            0
        ],
        [
            493,
            518
        ],
        [
            585,
            484
        ],
        [
            226,
            740
        ],
        [
            375,
            716
        ],
        [
            232,
            536
        ],
        [
            285,
            537
        ],
        [
            590,
            978
        ],
        [
            641,
            940
        ],
        [
            0,
            0
        ],
        [
            0,
            0
        ],
        [
            0,
            0
        ],
        [
            0,
            0
        ],
        [
            188.0,
            201.0,
            781.0,
            1070.0
        ]
    ],
    "75": [
        [
            359,
            394
        ],
        [
            368,
            364
        ],
        [
            0,
            0
        ],
        [
            432,
            367
        ],
        [
            0,
            0
        ],
        [
            492,
            518
        ],
        [
            586,
            484
        ],
        [
            227,
            741
        ],
        [
            376,
            719
        ],
        [
            233,
            544
        ],
        [
            281,
            545
        ],
        [
            591,
            975
        ],
        [
            644,
            938
        ],
        [
            0,
            0
        ],
        [
            0,
            0
        ],
        [
            0,
            0
        ],
        [
            0,
            0
        ],
        [
            190.0,
            200.0,
            781.0,
            1070.0
        ]
    ],
    "76": [
        [
            359,
            395
        ],
        [
            369,
            365
        ],
        [
            0,
            0
        ],
        [
            432,
            367
        ],
        [
            0,
            0
        ],
        [
            493,
            517
        ],
        [
            585,
            484
        ],
        [
            229,
            741
        ],
        [
            379,
            723
        ],
        [
            242,
            552
        ],
        [
            290,
            556
        ],
        [
            592,
            973
        ],
        [
            643,
            936
        ],
        [
            0,
            0
        ],
        [
            0,
            0
        ],
        [
            0,
            0
        ],
        [
            0,
            0
        ],
        [
            192.0,
            200.0,
            781.0,
            1070.0
        ]
    ],
    "77": [
        [
            360,
            395
        ],
        [
            369,
            365
        ],
        [
            0,
            0
        ],
        [
            431,
            368
        ],
        [
            0,
            0
        ],
        [
            490,
            516
        ],
        [
            587,
            485
        ],
        [
            231,
            742
        ],
        [
            383,
            725
        ],
        [
            263,
            560
        ],
        [
            304,
            564
        ],
        [
            592,
            971
        ],
        [
            647,
            935
        ],
        [
            0,
            0
        ],
        [
            0,
            0
        ],
        [
            0,
            0
        ],
        [
            0,
            0
        ],
        [
            193.0,
            201.0,
            781.0,
            1070.0
        ]
    ],
    "78": [
        [
            360,
            396
        ],
        [
            369,
            366
        ],
        [
            0,
            0
        ],
        [
            429,
            369
        ],
        [
            0,
            0
        ],
        [
            484,
            517
        ],
        [
            590,
            484
        ],
        [
            233,
            745
        ],
        [
            392,
            716
        ],
        [
            272,
            574
        ],
        [
            0,
            0
        ],
        [
            594,
            967
        ],
        [
            655,
            930
        ],
        [
            0,
            0
        ],
        [
            0,
            0
        ],
        [
            0,
            0
        ],
        [
            0,
            0
        ],
        [
            194.0,
            201.0,
            781.0,
            1070.0
        ]
    ],
    "79": [
        [
            360,
            396
        ],
        [
            369,
            367
        ],
        [
            0,
            0
        ],
        [
            429,
            369
        ],
        [
            0,
            0
        ],
        [
            482,
            517
        ],
        [
            592,
            483
        ],
        [
            232,
            743
        ],
        [
            396,
            714
        ],
        [
            282,
            586
        ],
        [
            0,
            0
        ],
        [
            595,
            965
        ],
        [
            659,
            929
        ],
        [
            0,
            0
        ],
        [
            0,
            0
        ],
        [
            0,
            0
        ],
        [
            0,
            0
        ],
        [
            194.0,
            201.0,
            781.0,
            1070.0
        ]
    ],
    "80": [
        [
            361,
            397
        ],
        [
            369,
            367
        ],
        [
            0,
            0
        ],
        [
            428,
            369
        ],
        [
            0,
            0
        ],
        [
            483,
            517
        ],
        [
            590,
            485
        ],
        [
            232,
            743
        ],
        [
            392,
            715
        ],
        [
            297,
            592
        ],
        [
            0,
            0
        ],
        [
            593,
            966
        ],
        [
            655,
            930
        ],
        [
            0,
            0
        ],
        [
            0,
            0
        ],
        [
            0,
            0
        ],
        [
            0,
            0
        ],
        [
            196.0,
            202.0,
            781.0,
            1070.0
        ]
    ],
    "81": [
        [
            361,
            398
        ],
        [
            369,
            368
        ],
        [
            0,
            0
        ],
        [
            427,
            369
        ],
        [
            0,
            0
        ],
        [
            481,
            514
        ],
        [
            589,
            484
        ],
        [
            233,
            737
        ],
        [
            0,
            0
        ],
        [
            314,
            603
        ],
        [
            0,
            0
        ],
        [
            593,
            965
        ],
        [
            655,
            931
        ],
        [
            0,
            0
        ],
        [
            0,
            0
        ],
        [
            0,
            0
        ],
        [
            0,
            0
        ],
        [
            196.0,
            203.0,
            781.0,
            1070.0
        ]
    ]
}